SPICE/QPP.py
SPICE/SPICE.py
SPICE/__init__.py
SPICE/util/__init__.py
SPICE/util/loadmat.py
SPICE_HSI-1.4.dist-info/LICENSE
SPICE_HSI-1.4.dist-info/METADATA
SPICE_HSI-1.4.dist-info/WHEEL
SPICE_HSI-1.4.dist-info/top_level.txt
SPICE_HSI-1.4.dist-info/RECORD
