Metadata-Version: 2.1
Name: SPICE-HSI
Version: 1.4
Summary: GatorSense Sparsity Promoting Iterated Constrained Endmembers Toolkit - Python Implementation
Home-page: https://faculty.eng.ufl.edu/machine-learning/
Author: The GatorSense team
Author-email: azare@ufl.edu
License: MIT
Keywords: plant phenotyping,bioinformatics,hyperspectral,machine-learning,sensing endmembers
Platform: Any
Classifier: Development Status :: 5 - Production/Stable
Classifier: Intended Audience :: Science/Research
Classifier: Topic :: Scientific/Engineering :: Bio-Informatics
Classifier: Topic :: Scientific/Engineering :: GIS
Classifier: License :: OSI Approved :: MIT License
Classifier: Programming Language :: Python :: 3
Classifier: Programming Language :: Python :: 3.6
Classifier: Programming Language :: Python :: 3.7
Requires-Dist: numpy
Requires-Dist: quadprog
Requires-Dist: cvxopt
Requires-Dist: scipy
